streamlit_custom_sidebar/__init__.py
streamlit_custom_sidebar/example.py
streamlit_custom_sidebar/Streamlit_template/__init__.py
streamlit_custom_sidebar/Streamlit_template/frontend/build/asset-manifest.json
streamlit_custom_sidebar/Streamlit_template/frontend/build/bootstrap.min.css
streamlit_custom_sidebar/Streamlit_template/frontend/build/bootstrap.min.css.map
streamlit_custom_sidebar/Streamlit_template/frontend/build/index.html
streamlit_custom_sidebar/Streamlit_template/frontend/build/static/js/main.a2b46d30.js
streamlit_custom_sidebar/Streamlit_template/frontend/build/static/js/main.a2b46d30.js.LICENSE.txt
streamlit_custom_sidebar/Streamlit_template/frontend/build/static/js/main.a2b46d30.js.map
streamlit_custom_sidebar/profile_sidebar/__init__.py
streamlit_custom_sidebar/profile_sidebar/frontend/build/asset-manifest.json
streamlit_custom_sidebar/profile_sidebar/frontend/build/bootstrap.min.css
streamlit_custom_sidebar/profile_sidebar/frontend/build/bootstrap.min.css.map
streamlit_custom_sidebar/profile_sidebar/frontend/build/index.html
streamlit_custom_sidebar/profile_sidebar/frontend/build/static/js/main.2039e60f.js
streamlit_custom_sidebar/profile_sidebar/frontend/build/static/js/main.2039e60f.js.LICENSE.txt
streamlit_custom_sidebar/profile_sidebar/frontend/build/static/js/main.2039e60f.js.map
streamlit_custom_sidebar/slim_expand_sidebar/__init__.py
streamlit_custom_sidebar/slim_expand_sidebar/frontend/build/asset-manifest.json
streamlit_custom_sidebar/slim_expand_sidebar/frontend/build/bootstrap.min.css
streamlit_custom_sidebar/slim_expand_sidebar/frontend/build/bootstrap.min.css.map
streamlit_custom_sidebar/slim_expand_sidebar/frontend/build/index.html
streamlit_custom_sidebar/slim_expand_sidebar/frontend/build/static/js/main.29d9cb3d.js
streamlit_custom_sidebar/slim_expand_sidebar/frontend/build/static/js/main.29d9cb3d.js.LICENSE.txt
streamlit_custom_sidebar/slim_expand_sidebar/frontend/build/static/js/main.29d9cb3d.js.map
streamlit_custom_sidebar_test-0.0.35.dist-info/LICENSE
streamlit_custom_sidebar_test-0.0.35.dist-info/METADATA
streamlit_custom_sidebar_test-0.0.35.dist-info/WHEEL
streamlit_custom_sidebar_test-0.0.35.dist-info/top_level.txt
streamlit_custom_sidebar_test-0.0.35.dist-info/RECORD
